symmorademo/__init__.py
symmorademo/core.py
symmorademo-0.8.0.dist-info/METADATA
symmorademo-0.8.0.dist-info/WHEEL
symmorademo-0.8.0.dist-info/top_level.txt
symmorademo-0.8.0.dist-info/RECORD
