Metadata-Version: 2.4
Name: symmorademo
Version: 0.8.0
Summary: A simple demo package for PyPI
Author-email: Symmora <symmora@gmail.com>
License: MIT
Project-URL: Homepage, https://github.com/symmora/symmorademo
Classifier: License :: OSI Approved :: MIT License
Classifier: Programming Language :: Python
Classifier: Programming Language :: Python :: 3
Requires-Python: >=3.8
Provides-Extra: dev
Requires-Dist: pytest; extra == "dev"
